poppingw/__init__.py
poppingw/cosmology.py
poppingw/gwfast.py
poppingw/likelihood/__init__.py
poppingw/likelihood/amplitude.py
poppingw/redshift_prior.py
poppingw/selection.py
poppingw/typing.py
poppingw/utils.py
poppingw-0.1.0.dist-info/METADATA
poppingw-0.1.0.dist-info/WHEEL
poppingw-0.1.0.dist-info/RECORD
