Metadata-Version: 2.3
Name: poppingw
Version: 0.1.0
Summary: 
Author: Mingzheng Li
Author-email: limz01@sjtu.edu.cn
Requires-Python: >=3.10
Classifier: Programming Language :: Python :: 3
Classifier: Programming Language :: Python :: 3.10
Classifier: Programming Language :: Python :: 3.11
Classifier: Programming Language :: Python :: 3.12
Classifier: Programming Language :: Python :: 3.13
Requires-Dist: astropy (>=6.0,<7.0)
Requires-Dist: bilby (>=2.2.0,<2.3.0)
Requires-Dist: gwfast (>=1.1.2,<2.0.0)
Requires-Dist: h5py (>=3.12.1,<4.0.0)
Requires-Dist: numba (>=0.60.0,<0.61.0)
Requires-Dist: pandas (>=2.2.3,<3.0.0)
Requires-Dist: scipy (>=1.12.0,<1.13.0)
Requires-Dist: tqdm (>=4.67.1,<5.0.0)
